{
  "id": 15625876,
  "slug": "bath-lane-15625876",
  "name": "Bath Lane",
  "network": "lwn",
  "tags": {
    "from": "South Promenade",
    "highway_authority_ref": "CD/RW/7000",
    "name": "Bath Lane",
    "network": "lwn",
    "operator": "Newry, Mourne & Down District Council",
    "route": "foot",
    "to": "King Street",
    "type": "route"
  },
  "coordinates": [
    [
      -5.8897222,
      54.1999603
    ],
    [
      -5.8903973,
      54.1995978
    ],
    [
      -5.8903973,
      54.1995978
    ],
    [
      -5.890458,
      54.1995635
    ],
    [
      -5.890458,
      54.1995635
    ],
    [
      -5.8904915,
      54.1995447
    ],
    [
      -5.8904915,
      54.1995447
    ],
    [
      -5.8905534,
      54.1995097
    ],
    [
      -5.8905534,
      54.1995097
    ],
    [
      -5.8905689,
      54.199501
    ],
    [
      -5.8905833,
      54.1994924
    ],
    [
      -5.8905833,
      54.1994924
    ],
    [
      -5.8906451,
      54.1994556
    ],
    [
      -5.8906451,
      54.1994556
    ],
    [
      -5.8906719,
      54.1994397
    ],
    [
      -5.8906719,
      54.1994397
    ],
    [
      -5.8907385,
      54.1994
    ],
    [
      -5.8907385,
      54.1994
    ],
    [
      -5.8907704,
      54.199381
    ],
    [
      -5.8907704,
      54.199381
    ],
    [
      -5.8908287,
      54.1993463
    ],
    [
      -5.8908287,
      54.1993463
    ],
    [
      -5.8908683,
      54.1993228
    ],
    [
      -5.8908683,
      54.1993228
    ],
    [
      -5.8908997,
      54.199304
    ],
    [
      -5.8908997,
      54.199304
    ],
    [
      -5.8909378,
      54.1992814
    ],
    [
      -5.8909378,
      54.1992814
    ],
    [
      -5.89099,
      54.1992503
    ]
  ]
}