{
  "id": 8368262,
  "slug": "kenn-to-haldon-trail-8368262",
  "name": "Kenn to Haldon Trail",
  "tags": {
    "name": "Kenn to Haldon Trail",
    "ref": "KHT",
    "route": "hiking",
    "type": "route"
  },
  "coordinates": [
    [
      -3.5263713,
      50.6604001
    ],
    [
      -3.526336,
      50.6603305
    ],
    [
      -3.5263234,
      50.6602622
    ],
    [
      -3.5263178,
      50.6602073
    ],
    [
      -3.526329,
      50.6600832
    ],
    [
      -3.5263868,
      50.6599615
    ],
    [
      -3.5264226,
      50.659898
    ],
    [
      -3.5264538,
      50.6598427
    ],
    [
      -3.5265023,
      50.6597713
    ],
    [
      -3.5267451,
      50.6593952
    ],
    [
      -3.5268594,
      50.6592995
    ],
    [
      -3.5268594,
      50.6592995
    ],
    [
      -3.5268026,
      50.6590169
    ],
    [
      -3.5268026,
      50.6590169
    ],
    [
      -3.5265112,
      50.6589245
    ],
    [
      -3.5261808,
      50.6588605
    ],
    [
      -3.525999,
      50.6588043
    ],
    [
      -3.5258086,
      50.6587172
    ],
    [
      -3.5160031,
      50.6493163
    ],
    [
      -3.5156168,
      50.6500937
    ],
    [
      -3.5153968,
      50.6507797
    ],
    [
      -3.5149982,
      50.6516368
    ],
    [
      -3.514964,
      50.6519389
    ],
    [
      -3.5144848,
      50.6520618
    ],
    [
      -3.5140656,
      50.6522473
    ],
    [
      -3.5138717,
      50.6524575
    ],
    [
      -3.5137617,
      50.6530051
    ],
    [
      -3.5139267,
      50.6534638
    ],
    [
      -3.5142645,
      50.6540705
    ],
    [
      -3.5142904,
      50.654117
    ],
    [
      -3.5146063,
      50.6544656
    ],
    [
      -3.5153134,
      50.6548273
    ],
    [
      -3.5165437,
      50.6555521
    ],
    [
      -3.517832,
      50.6563453
    ],
    [
      -3.5185111,
      50.6566827
    ],
    [
      -3.5193193,
      50.6570457
    ],
    [
      -3.520434,
      50.6572943
    ],
    [
      -3.5218298,
      50.6577016
    ],
    [
      -3.5229242,
      50.6579843
    ],
    [
      -3.5242975,
      50.6581611
    ],
    [
      -3.5251343,
      50.658406
    ],
    [
      -3.5251975,
      50.6584384
    ],
    [
      -3.5255861,
      50.6586213
    ],
    [
      -3.5258086,
      50.6587172
    ],
    [
      -3.5162914,
      50.6461014
    ],
    [
      -3.5165298,
      50.6460111
    ],
    [
      -3.5168619,
      50.6458583
    ],
    [
      -3.5171294,
      50.6457065
    ],
    [
      -3.5172841,
      50.6455539
    ],
    [
      -3.5170899,
      50.6452515
    ],
    [
      -3.5167492,
      50.6448793
    ],
    [
      -3.5161945,
      50.6444446
    ],
    [
      -3.515877,
      50.644199
    ],
    [
      -3.515716,
      50.6439537
    ],
    [
      -3.5155809,
      50.6436302
    ],
    [
      -3.5155642,
      50.6432237
    ],
    [
      -3.515509,
      50.6429985
    ],
    [
      -3.5149468,
      50.6429135
    ],
    [
      -3.514347,
      50.6429822
    ],
    [
      -3.5140776,
      50.6429782
    ],
    [
      -3.513846,
      50.6428961
    ],
    [
      -3.513586,
      50.6428105
    ],
    [
      -3.513448,
      50.642509
    ],
    [
      -3.5131856,
      50.6422827
    ],
    [
      -3.5128246,
      50.642165
    ],
    [
      -3.5125307,
      50.6420497
    ],
    [
      -3.5125012,
      50.6418313
    ],
    [
      -3.5127962,
      50.641784
    ],
    [
      -3.513176,
      50.641735
    ],
    [
      -3.5133112,
      50.6415609
    ],
    [
      -3.5132543,
      50.6410883
    ],
    [
      -3.5133294,
      50.6408299
    ],
    [
      -3.5135202,
      50.6404664
    ],
    [
      -3.5135747,
      50.6401575
    ],
    [
      -3.5136565,
      50.6397759
    ],
    [
      -3.5138311,
      50.6393976
    ],
    [
      -3.5160031,
      50.6493163
    ],
    [
      -3.515914,
      50.6491143
    ],
    [
      -3.5158172,
      50.6490484
    ],
    [
      -3.5155033,
      50.6490153
    ],
    [
      -3.5152728,
      50.6490086
    ],
    [
      -3.5151081,
      50.6489102
    ],
    [
      -3.5149767,
      50.6488166
    ],
    [
      -3.5149668,
      50.6486477
    ],
    [
      -3.5149571,
      50.6484969
    ],
    [
      -3.514685,
      50.6477581
    ],
    [
      -3.5146636,
      50.6476249
    ],
    [
      -3.5147437,
      50.6475439
    ],
    [
      -3.515017,
      50.6473889
    ],
    [
      -3.5154657,
      50.6471827
    ],
    [
      -3.5156347,
      50.647002
    ],
    [
      -3.5157593,
      50.646751
    ],
    [
      -3.5159319,
      50.6464717
    ],
    [
      -3.5162914,
      50.6461014
    ],
    [
      -3.5138311,
      50.6393976
    ],
    [
      -3.514261,
      50.639192
    ],
    [
      -3.5143746,
      50.6390772
    ],
    [
      -3.5143873,
      50.6388463
    ],
    [
      -3.5144357,
      50.6386381
    ],
    [
      -3.5146482,
      50.638287
    ],
    [
      -3.5147556,
      50.6381309
    ],
    [
      -3.5153063,
      50.6378342
    ],
    [
      -3.51627,
      50.6373356
    ],
    [
      -3.5169633,
      50.6369015
    ],
    [
      -3.5172559,
      50.636712
    ],
    [
      -3.5172559,
      50.636712
    ],
    [
      -3.5175821,
      50.6366185
    ],
    [
      -3.5178367,
      50.6365999
    ],
    [
      -3.5183254,
      50.6365184
    ],
    [
      -3.5183254,
      50.6365184
    ],
    [
      -3.5193539,
      50.6366385
    ],
    [
      -3.5193539,
      50.6366385
    ],
    [
      -3.5198834,
      50.6365491
    ],
    [
      -3.5203504,
      50.6364951
    ],
    [
      -3.5213531,
      50.6363293
    ],
    [
      -3.5221434,
      50.6360956
    ],
    [
      -3.523584,
      50.63541
    ],
    [
      -3.5241353,
      50.6350092
    ],
    [
      -3.5247265,
      50.6346207
    ],
    [
      -3.5248765,
      50.63445
    ],
    [
      -3.5260737,
      50.6338468
    ],
    [
      -3.526821,
      50.6335159
    ],
    [
      -3.5276748,
      50.6330973
    ],
    [
      -3.5286044,
      50.6327011
    ],
    [
      -3.5290665,
      50.6324592
    ],
    [
      -3.5296423,
      50.632135
    ],
    [
      -3.5296423,
      50.632135
    ],
    [
      -3.5301209,
      50.6320609
    ],
    [
      -3.5306151,
      50.6319504
    ],
    [
      -3.5310758,
      50.631934
    ],
    [
      -3.531622,
      50.6317993
    ],
    [
      -3.5320679,
      50.6317247
    ],
    [
      -3.5322804,
      50.6316958
    ],
    [
      -3.5322804,
      50.6316958
    ],
    [
      -3.5324681,
      50.6316829
    ],
    [
      -3.5332111,
      50.6318724
    ],
    [
      -3.5330626,
      50.6317679
    ],
    [
      -3.5329172,
      50.6317772
    ],
    [
      -3.5327681,
      50.6318445
    ],
    [
      -3.5325615,
      50.6318098
    ],
    [
      -3.5324681,
      50.6316829
    ],
    [
      -3.5357463,
      50.6360909
    ],
    [
      -3.5350235,
      50.635578
    ],
    [
      -3.5347966,
      50.6354535
    ],
    [
      -3.5346792,
      50.6352943
    ],
    [
      -3.5349157,
      50.6350568
    ],
    [
      -3.5348842,
      50.6349937
    ],
    [
      -3.5345507,
      50.6347632
    ],
    [
      -3.5339833,
      50.6340761
    ],
    [
      -3.5336419,
      50.6333597
    ],
    [
      -3.533467,
      50.6327799
    ],
    [
      -3.5333309,
      50.6326173
    ],
    [
      -3.5333202,
      50.6322451
    ],
    [
      -3.5332111,
      50.6318724
    ],
    [
      -3.5387167,
      50.6414994
    ],
    [
      -3.538497,
      50.641446
    ],
    [
      -3.538369,
      50.6412802
    ],
    [
      -3.5382594,
      50.6408773
    ],
    [
      -3.5377296,
      50.6398528
    ],
    [
      -3.5371932,
      50.6392676
    ],
    [
      -3.5371232,
      50.6390127
    ],
    [
      -3.5370475,
      50.638737
    ],
    [
      -3.536882,
      50.6382856
    ],
    [
      -3.5368374,
      50.6378548
    ],
    [
      -3.5367453,
      50.6375352
    ],
    [
      -3.5362061,
      50.6367908
    ],
    [
      -3.5358215,
      50.6362053
    ],
    [
      -3.5357463,
      50.6360909
    ],
    [
      -3.5387167,
      50.6414994
    ],
    [
      -3.5386702,
      50.6417321
    ],
    [
      -3.5386059,
      50.6420042
    ],
    [
      -3.5382045,
      50.6420851
    ],
    [
      -3.538028,
      50.64217
    ],
    [
      -3.5379132,
      50.6424295
    ],
    [
      -3.5378877,
      50.6426012
    ],
    [
      -3.5378869,
      50.6427607
    ],
    [
      -3.5378488,
      50.6429614
    ],
    [
      -3.5379151,
      50.6432024
    ],
    [
      -3.5281312,
      50.6479453
    ],
    [
      -3.5289963,
      50.6476089
    ],
    [
      -3.5303053,
      50.6472007
    ],
    [
      -3.5313781,
      50.646983
    ],
    [
      -3.5316571,
      50.6469014
    ],
    [
      -3.532011,
      50.6467897
    ],
    [
      -3.5326269,
      50.6464031
    ],
    [
      -3.5330745,
      50.6459569
    ],
    [
      -3.5335086,
      50.6453407
    ],
    [
      -3.5342535,
      50.6447924
    ],
    [
      -3.5349852,
      50.6443704
    ],
    [
      -3.5361997,
      50.6438479
    ],
    [
      -3.5377296,
      50.6432411
    ],
    [
      -3.5379151,
      50.6432024
    ],
    [
      -3.525356,
      50.6500342
    ],
    [
      -3.5259745,
      50.6497208
    ],
    [
      -3.526793,
      50.6492068
    ],
    [
      -3.5274063,
      50.6488754
    ],
    [
      -3.5276704,
      50.6485581
    ],
    [
      -3.5278207,
      50.6483109
    ],
    [
      -3.5281312,
      50.6479453
    ],
    [
      -3.52605,
      50.6537868
    ],
    [
      -3.5261162,
      50.6532062
    ],
    [
      -3.5260269,
      50.6527277
    ],
    [
      -3.5258772,
      50.6524899
    ],
    [
      -3.5257045,
      50.6521406
    ],
    [
      -3.5256104,
      50.6518607
    ],
    [
      -3.525568,
      50.651576
    ],
    [
      -3.525656,
      50.6511937
    ],
    [
      -3.5256144,
      50.6508971
    ],
    [
      -3.5254899,
      50.6504917
    ],
    [
      -3.525356,
      50.6500342
    ],
    [
      -3.5267495,
      50.6573297
    ],
    [
      -3.5266547,
      50.6569786
    ],
    [
      -3.5266226,
      50.6569156
    ],
    [
      -3.5264327,
      50.6565431
    ],
    [
      -3.5261716,
      50.6557904
    ],
    [
      -3.5261425,
      50.6557064
    ],
    [
      -3.52604,
      50.6551258
    ],
    [
      -3.5259717,
      50.6543574
    ],
    [
      -3.52605,
      50.6537868
    ],
    [
      -3.5261809,
      50.6583037
    ],
    [
      -3.5264242,
      50.6578665
    ],
    [
      -3.5266208,
      50.6575555
    ],
    [
      -3.5267495,
      50.6573297
    ],
    [
      -3.5258086,
      50.6587172
    ],
    [
      -3.5259127,
      50.6586097
    ],
    [
      -3.5261809,
      50.6583037
    ]
  ]
}