{
  "id": 17359332,
  "slug": "storth-trail-17359332",
  "name": "Storth Trail",
  "network": "lwn",
  "tags": {
    "name": "Storth Trail",
    "network": "lwn",
    "network:type": "local",
    "route": "foot",
    "source": "https://hincastertrailway.co.uk/users/UserFiles/File/Storth%20Trail_A4_3fold.pdf",
    "type": "route",
    "website": "https://hincastertrailway.co.uk/"
  },
  "coordinates": [
    [
      -2.8090728,
      54.2157378
    ],
    [
      -2.8084358,
      54.2161813
    ],
    [
      -2.8077647,
      54.2166269
    ],
    [
      -2.8062695,
      54.2173124
    ],
    [
      -2.8038398,
      54.2182827
    ],
    [
      -2.8020803,
      54.2192173
    ],
    [
      -2.8014718,
      54.2196603
    ],
    [
      -2.8092652,
      54.2157945
    ],
    [
      -2.8090728,
      54.2157378
    ],
    [
      -2.8085142,
      54.2168188
    ],
    [
      -2.8085854,
      54.2166082
    ],
    [
      -2.8086044,
      54.2165721
    ],
    [
      -2.8086889,
      54.2164113
    ],
    [
      -2.808977,
      54.2160276
    ],
    [
      -2.8092652,
      54.2157945
    ],
    [
      -2.8085142,
      54.2168188
    ],
    [
      -2.8084684,
      54.2168097
    ],
    [
      -2.8081657,
      54.216831
    ],
    [
      -2.8077325,
      54.2169021
    ],
    [
      -2.8076486,
      54.2168899
    ],
    [
      -2.8076057,
      54.2168659
    ],
    [
      -2.8075717,
      54.2167669
    ],
    [
      -2.8075717,
      54.2167669
    ],
    [
      -2.8075964,
      54.2165196
    ],
    [
      -2.8075964,
      54.2165196
    ],
    [
      -2.8075835,
      54.2164898
    ],
    [
      -2.8075376,
      54.2164059
    ],
    [
      -2.8073528,
      54.2163137
    ],
    [
      -2.8069677,
      54.2161363
    ],
    [
      -2.8066379,
      54.2159614
    ],
    [
      -2.8065921,
      54.2159038
    ],
    [
      -2.8066192,
      54.2157143
    ],
    [
      -2.8066166,
      54.2156761
    ],
    [
      -2.8057512,
      54.2106863
    ],
    [
      -2.8057553,
      54.2107255
    ],
    [
      -2.8057939,
      54.2110184
    ],
    [
      -2.8058355,
      54.2113269
    ],
    [
      -2.8058465,
      54.2114083
    ],
    [
      -2.8058533,
      54.2114958
    ],
    [
      -2.8058972,
      54.2120601
    ],
    [
      -2.8058948,
      54.2122106
    ],
    [
      -2.8058955,
      54.212786
    ],
    [
      -2.8059031,
      54.2130484
    ],
    [
      -2.805921,
      54.213283
    ],
    [
      -2.8059498,
      54.2134181
    ],
    [
      -2.8059583,
      54.2136359
    ],
    [
      -2.8060623,
      54.2140253
    ],
    [
      -2.8061975,
      54.2142216
    ],
    [
      -2.80633,
      54.2144378
    ],
    [
      -2.806333,
      54.2144457
    ],
    [
      -2.8064255,
      54.2146882
    ],
    [
      -2.8064871,
      54.214854
    ],
    [
      -2.8065673,
      54.2149981
    ],
    [
      -2.8067814,
      54.2152061
    ],
    [
      -2.8068712,
      54.2153105
    ],
    [
      -2.806902,
      54.2153726
    ],
    [
      -2.8069048,
      54.2154325
    ],
    [
      -2.8068566,
      54.2155227
    ],
    [
      -2.8067541,
      54.2156041
    ],
    [
      -2.8066166,
      54.2156761
    ],
    [
      -2.8057512,
      54.2106863
    ],
    [
      -2.805337,
      54.2107824
    ],
    [
      -2.804957,
      54.2109034
    ],
    [
      -2.8041525,
      54.211166
    ],
    [
      -2.803767,
      54.2113052
    ],
    [
      -2.803603,
      54.2113712
    ],
    [
      -2.8033036,
      54.2114781
    ],
    [
      -2.8031619,
      54.2115009
    ],
    [
      -2.8026445,
      54.211459
    ],
    [
      -2.8025479,
      54.2116786
    ],
    [
      -2.8023982,
      54.2119721
    ],
    [
      -2.8021074,
      54.2121284
    ],
    [
      -2.8021517,
      54.2152888
    ],
    [
      -2.8021543,
      54.215269
    ],
    [
      -2.802387,
      54.2149473
    ],
    [
      -2.8024406,
      54.2143889
    ],
    [
      -2.8022904,
      54.2137866
    ],
    [
      -2.8022797,
      54.2130902
    ],
    [
      -2.8022797,
      54.2128615
    ],
    [
      -2.8022797,
      54.2127577
    ],
    [
      -2.8021271,
      54.2121736
    ],
    [
      -2.8021074,
      54.2121284
    ],
    [
      -2.8021517,
      54.2152888
    ],
    [
      -2.8021129,
      54.2152956
    ],
    [
      -2.8015306,
      54.2153989
    ],
    [
      -2.8014301,
      54.2154298
    ],
    [
      -2.8013339,
      54.2154961
    ],
    [
      -2.8013114,
      54.2155273
    ],
    [
      -2.8011844,
      54.2157188
    ],
    [
      -2.8009545,
      54.2161523
    ],
    [
      -2.8001985,
      54.2167728
    ],
    [
      -2.8001985,
      54.2167728
    ],
    [
      -2.7995797,
      54.2192689
    ],
    [
      -2.7994928,
      54.2196193
    ],
    [
      -2.7990823,
      54.2203169
    ],
    [
      -2.7987038,
      54.2205982
    ],
    [
      -2.798706,
      54.2207606
    ],
    [
      -2.8000478,
      54.2204471
    ],
    [
      -2.7999067,
      54.2203661
    ],
    [
      -2.7998173,
      54.220371
    ],
    [
      -2.7992545,
      54.2204856
    ],
    [
      -2.798706,
      54.2207606
    ],
    [
      -2.8013201,
      54.2195788
    ],
    [
      -2.8000478,
      54.2204471
    ],
    [
      -2.8014718,
      54.2196603
    ],
    [
      -2.8013201,
      54.2195788
    ]
  ]
}