{
  "id": 19377928,
  "slug": "studley-royal-deer-park-walk-19377928",
  "name": "Studley Royal Deer Park Walk",
  "network": "lwn",
  "tags": {
    "distance": "4.8",
    "dog": "leashed",
    "duration": "01:00",
    "from": "Fountains Abbey Visitor Centre, grid ref: SE272687",
    "name": "Studley Royal Deer Park Walk",
    "network": "lwn",
    "network:type": "lwn",
    "operator": "National Trust",
    "roundtrip": "yes",
    "route": "foot",
    "to": "Fountains Abbey Visitor Centre, grid ref: SE272687",
    "tourism": "yes",
    "type": "route"
  },
  "coordinates": [
    [
      -1.5844238,
      54.1129539
    ],
    [
      -1.5843172,
      54.1129647
    ],
    [
      -1.5842407,
      54.1129724
    ],
    [
      -1.5843118,
      54.1131815
    ],
    [
      -1.5842301,
      54.113191
    ],
    [
      -1.5842655,
      54.1133061
    ],
    [
      -1.5842414,
      54.1133423
    ],
    [
      -1.5842441,
      54.1133659
    ],
    [
      -1.5842649,
      54.1133835
    ],
    [
      -1.5842997,
      54.1133913
    ],
    [
      -1.5843453,
      54.1133835
    ],
    [
      -1.5843701,
      54.1133659
    ],
    [
      -1.584397,
      54.1133517
    ],
    [
      -1.5845814,
      54.1133332
    ],
    [
      -1.5845706,
      54.1132954
    ],
    [
      -1.5849007,
      54.1132568
    ],
    [
      -1.5849837,
      54.1132467
    ],
    [
      -1.5849897,
      54.1132653
    ],
    [
      -1.585089,
      54.1132534
    ],
    [
      -1.584979,
      54.1129351
    ],
    [
      -1.5851037,
      54.1129201
    ],
    [
      -1.5850822,
      54.1128719
    ],
    [
      -1.5850347,
      54.1128788
    ],
    [
      -1.584987,
      54.1127448
    ],
    [
      -1.5847136,
      54.1127684
    ],
    [
      -1.5847312,
      54.1128184
    ],
    [
      -1.584534,
      54.1128422
    ],
    [
      -1.5845654,
      54.1129356
    ],
    [
      -1.5845713,
      54.1129532
    ],
    [
      -1.5846743,
      54.112942
    ],
    [
      -1.5847604,
      54.1129666
    ],
    [
      -1.5848549,
      54.1129936
    ],
    [
      -1.5848999,
      54.1131395
    ],
    [
      -1.5848613,
      54.1131443
    ],
    [
      -1.5846303,
      54.1131678
    ],
    [
      -1.5844735,
      54.1131049
    ],
    [
      -1.5844678,
      54.1130878
    ],
    [
      -1.5844443,
      54.1130162
    ],
    [
      -1.5844238,
      54.1129539
    ],
    [
      -1.5878061,
      54.1120963
    ],
    [
      -1.5850541,
      54.1124618
    ],
    [
      -1.5854382,
      54.1134845
    ],
    [
      -1.5862343,
      54.1134413
    ],
    [
      -1.586823,
      54.1128738
    ],
    [
      -1.587275,
      54.1125719
    ],
    [
      -1.5878061,
      54.1120963
    ],
    [
      -1.5863248,
      54.1121416
    ],
    [
      -1.5866634,
      54.112079
    ],
    [
      -1.5877806,
      54.1119241
    ],
    [
      -1.5875261,
      54.1113247
    ],
    [
      -1.5855933,
      54.1116048
    ],
    [
      -1.5857961,
      54.1120287
    ],
    [
      -1.5858187,
      54.1121011
    ],
    [
      -1.5858465,
      54.1121071
    ],
    [
      -1.5859057,
      54.1121377
    ],
    [
      -1.5863248,
      54.1121416
    ],
    [
      -1.5847136,
      54.1127684
    ],
    [
      -1.5846869,
      54.1126923
    ],
    [
      -1.5844897,
      54.1127161
    ],
    [
      -1.584534,
      54.1128422
    ],
    [
      -1.5847312,
      54.1128184
    ],
    [
      -1.5847136,
      54.1127684
    ],
    [
      -1.5837774,
      54.1136362
    ],
    [
      -1.583551,
      54.1132126
    ],
    [
      -1.5832249,
      54.1126724
    ],
    [
      -1.5811521,
      54.1129388
    ],
    [
      -1.5816597,
      54.1135078
    ],
    [
      -1.5819465,
      54.1138292
    ],
    [
      -1.5837774,
      54.1136362
    ],
    [
      -1.5745425,
      54.1267971
    ],
    [
      -1.5742636,
      54.1267846
    ],
    [
      -1.5740034,
      54.1267626
    ],
    [
      -1.5738941,
      54.1267494
    ],
    [
      -1.5737432,
      54.1267311
    ],
    [
      -1.5731001,
      54.1266689
    ],
    [
      -1.5745425,
      54.1267971
    ],
    [
      -1.5742636,
      54.1267846
    ],
    [
      -1.5740034,
      54.1267626
    ],
    [
      -1.5738941,
      54.1267494
    ],
    [
      -1.5737432,
      54.1267311
    ],
    [
      -1.5731001,
      54.1266689
    ],
    [
      -1.5750584,
      54.1269073
    ],
    [
      -1.5745425,
      54.1267971
    ],
    [
      -1.5750739,
      54.1269401
    ],
    [
      -1.5750584,
      54.1269073
    ],
    [
      -1.5750739,
      54.1269401
    ],
    [
      -1.5758044,
      54.1268466
    ],
    [
      -1.5758044,
      54.1268466
    ],
    [
      -1.575921,
      54.1268119
    ],
    [
      -1.5760005,
      54.1267519
    ],
    [
      -1.5760218,
      54.1267052
    ],
    [
      -1.576024,
      54.1266263
    ],
    [
      -1.5760204,
      54.1265268
    ],
    [
      -1.5760562,
      54.1264503
    ],
    [
      -1.5762483,
      54.1262956
    ],
    [
      -1.5766023,
      54.126019
    ],
    [
      -1.5766828,
      54.1258524
    ],
    [
      -1.5810836,
      54.1184704
    ],
    [
      -1.5810985,
      54.1186398
    ],
    [
      -1.5810473,
      54.1187159
    ],
    [
      -1.5808672,
      54.1189864
    ],
    [
      -1.580695,
      54.1198042
    ],
    [
      -1.5804321,
      54.1201249
    ],
    [
      -1.580121,
      54.1204424
    ],
    [
      -1.5800405,
      54.12076
    ],
    [
      -1.5796816,
      54.1211684
    ],
    [
      -1.5791768,
      54.1216434
    ],
    [
      -1.5788746,
      54.1219154
    ],
    [
      -1.5788289,
      54.1221045
    ],
    [
      -1.578772,
      54.1223375
    ],
    [
      -1.5785497,
      54.1226366
    ],
    [
      -1.5786034,
      54.1231113
    ],
    [
      -1.5786248,
      54.1237966
    ],
    [
      -1.5787286,
      54.124408
    ],
    [
      -1.5787494,
      54.1245592
    ],
    [
      -1.5787429,
      54.1246307
    ],
    [
      -1.5786914,
      54.1246865
    ],
    [
      -1.5786347,
      54.1247087
    ],
    [
      -1.5784966,
      54.1247307
    ],
    [
      -1.5783486,
      54.1248057
    ],
    [
      -1.5782595,
      54.124908
    ],
    [
      -1.5782064,
      54.1251765
    ],
    [
      -1.5780654,
      54.1253236
    ],
    [
      -1.5778299,
      54.1254418
    ],
    [
      -1.5771228,
      54.1256795
    ],
    [
      -1.5766828,
      54.1258524
    ],
    [
      -1.5810283,
      54.1182419
    ],
    [
      -1.5810724,
      54.1182907
    ],
    [
      -1.5810941,
      54.1183384
    ],
    [
      -1.5811007,
      54.1184125
    ],
    [
      -1.5810836,
      54.1184704
    ],
    [
      -1.5810283,
      54.1182419
    ],
    [
      -1.5810643,
      54.1181429
    ],
    [
      -1.5810697,
      54.1180654
    ],
    [
      -1.5810697,
      54.1180654
    ],
    [
      -1.5812051,
      54.1180384
    ],
    [
      -1.5813027,
      54.1180225
    ],
    [
      -1.581355,
      54.1180185
    ],
    [
      -1.5813959,
      54.1180154
    ],
    [
      -1.5814888,
      54.1180134
    ],
    [
      -1.5815653,
      54.1180152
    ],
    [
      -1.5820504,
      54.1175367
    ],
    [
      -1.5818626,
      54.1177388
    ],
    [
      -1.5815855,
      54.1179887
    ],
    [
      -1.5815653,
      54.1180152
    ],
    [
      -1.5820504,
      54.1175367
    ],
    [
      -1.5821841,
      54.1173927
    ],
    [
      -1.5826863,
      54.1166903
    ],
    [
      -1.5832261,
      54.1160115
    ],
    [
      -1.5840787,
      54.1147635
    ],
    [
      -1.5842079,
      54.1146138
    ],
    [
      -1.5844115,
      54.114523
    ],
    [
      -1.5845942,
      54.1144483
    ],
    [
      -1.5848517,
      54.1142886
    ],
    [
      -1.5849596,
      54.1142104
    ],
    [
      -1.5849596,
      54.1142104
    ],
    [
      -1.5850789,
      54.1140868
    ],
    [
      -1.5853843,
      54.1139644
    ],
    [
      -1.5853843,
      54.1139644
    ],
    [
      -1.5854234,
      54.1139226
    ],
    [
      -1.585389,
      54.1138713
    ],
    [
      -1.5853561,
      54.1137955
    ],
    [
      -1.5851528,
      54.1137648
    ],
    [
      -1.5850953,
      54.1137612
    ],
    [
      -1.5850624,
      54.1137413
    ],
    [
      -1.5850173,
      54.1137063
    ],
    [
      -1.5849345,
      54.1132972
    ],
    [
      -1.5848417,
      54.1134544
    ],
    [
      -1.5848828,
      54.1135162
    ],
    [
      -1.5849658,
      54.1135887
    ],
    [
      -1.5850027,
      54.1136239
    ],
    [
      -1.5850056,
      54.1136404
    ],
    [
      -1.5850173,
      54.1137063
    ],
    [
      -1.5849345,
      54.1132972
    ],
    [
      -1.5849141,
      54.1132729
    ],
    [
      -1.5849007,
      54.1132568
    ],
    [
      -1.5849007,
      54.1132568
    ],
    [
      -1.5848613,
      54.1131443
    ],
    [
      -1.5849007,
      54.1132568
    ],
    [
      -1.5848613,
      54.1131443
    ],
    [
      -1.5849345,
      54.1132972
    ],
    [
      -1.5849141,
      54.1132729
    ],
    [
      -1.5849007,
      54.1132568
    ],
    [
      -1.5849345,
      54.1132972
    ],
    [
      -1.5848417,
      54.1134544
    ],
    [
      -1.5848828,
      54.1135162
    ],
    [
      -1.5849658,
      54.1135887
    ],
    [
      -1.5850027,
      54.1136239
    ],
    [
      -1.5850056,
      54.1136404
    ],
    [
      -1.5850173,
      54.1137063
    ],
    [
      -1.5853843,
      54.1139644
    ],
    [
      -1.5854234,
      54.1139226
    ],
    [
      -1.585389,
      54.1138713
    ],
    [
      -1.5853561,
      54.1137955
    ],
    [
      -1.5851528,
      54.1137648
    ],
    [
      -1.5850953,
      54.1137612
    ],
    [
      -1.5850624,
      54.1137413
    ],
    [
      -1.5850173,
      54.1137063
    ],
    [
      -1.5849596,
      54.1142104
    ],
    [
      -1.5850789,
      54.1140868
    ],
    [
      -1.5853843,
      54.1139644
    ],
    [
      -1.5820504,
      54.1175367
    ],
    [
      -1.5821841,
      54.1173927
    ],
    [
      -1.5826863,
      54.1166903
    ],
    [
      -1.5832261,
      54.1160115
    ],
    [
      -1.5840787,
      54.1147635
    ],
    [
      -1.5842079,
      54.1146138
    ],
    [
      -1.5844115,
      54.114523
    ],
    [
      -1.5845942,
      54.1144483
    ],
    [
      -1.5848517,
      54.1142886
    ],
    [
      -1.5849596,
      54.1142104
    ],
    [
      -1.5820504,
      54.1175367
    ],
    [
      -1.5818626,
      54.1177388
    ],
    [
      -1.5815855,
      54.1179887
    ],
    [
      -1.5815653,
      54.1180152
    ],
    [
      -1.5810697,
      54.1180654
    ],
    [
      -1.5812051,
      54.1180384
    ],
    [
      -1.5813027,
      54.1180225
    ],
    [
      -1.581355,
      54.1180185
    ],
    [
      -1.5813959,
      54.1180154
    ],
    [
      -1.5814888,
      54.1180134
    ],
    [
      -1.5815653,
      54.1180152
    ],
    [
      -1.5798048,
      54.11844
    ],
    [
      -1.580167,
      54.1183086
    ],
    [
      -1.5803777,
      54.118238
    ],
    [
      -1.5806209,
      54.1181714
    ],
    [
      -1.5810697,
      54.1180654
    ],
    [
      -1.5747695,
      54.1202411
    ],
    [
      -1.5770636,
      54.1196156
    ],
    [
      -1.5779758,
      54.1193713
    ],
    [
      -1.5781274,
      54.1193309
    ],
    [
      -1.5782322,
      54.1193029
    ],
    [
      -1.5785348,
      54.1192087
    ],
    [
      -1.5788057,
      54.1190545
    ],
    [
      -1.5790423,
      54.1188355
    ],
    [
      -1.5792724,
      54.1186689
    ],
    [
      -1.5798048,
      54.11844
    ],
    [
      -1.5747695,
      54.1202411
    ],
    [
      -1.5724368,
      54.120875
    ],
    [
      -1.5702412,
      54.1214818
    ],
    [
      -1.5717878,
      54.1210588
    ],
    [
      -1.571943,
      54.1210163
    ],
    [
      -1.5720502,
      54.1209856
    ],
    [
      -1.5724368,
      54.120875
    ],
    [
      -1.5654423,
      54.1227917
    ],
    [
      -1.567479,
      54.1222358
    ],
    [
      -1.5690822,
      54.1217982
    ],
    [
      -1.5702412,
      54.1214818
    ],
    [
      -1.5654423,
      54.1227917
    ],
    [
      -1.5651164,
      54.1230906
    ],
    [
      -1.5648053,
      54.1233892
    ],
    [
      -1.5642849,
      54.1237319
    ],
    [
      -1.5634266,
      54.1244109
    ],
    [
      -1.5626863,
      54.1249674
    ],
    [
      -1.5621445,
      54.1253509
    ],
    [
      -1.5618841,
      54.1256025
    ],
    [
      -1.5654423,
      54.1227917
    ],
    [
      -1.5651164,
      54.1230906
    ],
    [
      -1.5648053,
      54.1233892
    ],
    [
      -1.5642849,
      54.1237319
    ],
    [
      -1.5634266,
      54.1244109
    ],
    [
      -1.5626863,
      54.1249674
    ],
    [
      -1.5621445,
      54.1253509
    ],
    [
      -1.5618841,
      54.1256025
    ],
    [
      -1.5731001,
      54.1266689
    ],
    [
      -1.572914,
      54.1266719
    ],
    [
      -1.5728108,
      54.1266735
    ],
    [
      -1.5728108,
      54.1266735
    ],
    [
      -1.5726989,
      54.1266697
    ],
    [
      -1.5726989,
      54.1266697
    ],
    [
      -1.5725006,
      54.1265914
    ],
    [
      -1.5720858,
      54.1264028
    ],
    [
      -1.571755,
      54.1262487
    ],
    [
      -1.5715046,
      54.1261167
    ],
    [
      -1.5712863,
      54.1260883
    ],
    [
      -1.5707322,
      54.1261649
    ],
    [
      -1.5696253,
      54.1263493
    ],
    [
      -1.5686043,
      54.1265327
    ],
    [
      -1.5673383,
      54.1267727
    ],
    [
      -1.5665552,
      54.1269277
    ],
    [
      -1.5664066,
      54.1269571
    ],
    [
      -1.565441,
      54.127109
    ],
    [
      -1.5651675,
      54.1271457
    ],
    [
      -1.5649189,
      54.1270891
    ],
    [
      -1.5647437,
      54.1270053
    ],
    [
      -1.5643342,
      54.1268712
    ],
    [
      -1.5639229,
      54.1266123
    ],
    [
      -1.5633042,
      54.1261932
    ],
    [
      -1.5630896,
      54.1260591
    ],
    [
      -1.5626587,
      54.1259187
    ],
    [
      -1.5623207,
      54.1258191
    ],
    [
      -1.562065,
      54.1257091
    ],
    [
      -1.5619823,
      54.1256712
    ],
    [
      -1.5618841,
      54.1256025
    ]
  ]
}